LICENSE
MANIFEST.in
README.rst
setup.py
django_jsonfield_widget/__init__.py
django_jsonfield_widget/widgets.py
django_jsonfield_widget.egg-info/PKG-INFO
django_jsonfield_widget.egg-info/SOURCES.txt
django_jsonfield_widget.egg-info/dependency_links.txt
django_jsonfield_widget.egg-info/not-zip-safe
django_jsonfield_widget.egg-info/requires.txt
django_jsonfield_widget.egg-info/top_level.txt
django_jsonfield_widget/static/admin/js/django_jsonfield_widget/bundles/JsonFieldSchemaWidget.js
django_jsonfield_widget/templates/django_jsonfield_widget/jsonfield_schema_widget.html
django_jsonfield_widget/templatetags/__init__.py
django_jsonfield_widget/templatetags/jsonify.py