Metadata-Version: 1.0
Name: django-jsonfield-widget
Version: 0.1.0
Summary: An admin widget for the Hstore, this widget usefulness is to have dynamic fields for a given model.
Home-page: https://bitbucket.org/deusesprl/django_jsonfield_widget
Author: Maxime Deuse
Author-email: m.deuse@deuse.be
License: MIT
Platform: UNKNOWN
